pdsavails
