Metadata-Version: 1.0
Name: pdsavails
Version: 1.0.4
Summary: Integration library for PDSAvails
Home-page: https://github.com/premieredigital/PDSAvails/
Author: David Litwin
Author-email: david@premieredigital.net
License: MIT License
Platform: any
Classifier: Development Status :: 4 - Beta
Classifier: Intended Audience :: Developers
Classifier: License :: OSI Approved :: MIT License
Classifier: Operating System :: OS Independent
Classifier: Programming Language :: Python
Classifier: Programming Language :: Python :: 2.6
Classifier: Programming Language :: Python :: 2.7
Classifier: Topic :: Software Development :: Libraries :: Python Modules
